{
    "build_time": "2026-05-26T14:14:18.325858304",
    "data": {},
    "latest_commit": "8ad24e0",
    "name": "surge-xt",
    "project_repo": "https://github.com/surge-synthesizer/surge",
    "recent_commits": [
        {
            "author": "EvilDragon",
            "commit": "8ad24e0",
            "date": "2026-05-26T15:27:18+02:00",
            "message": "Add quantized param drag (via Ctrl) to FX plugin (#8401)"
        },
        {
            "author": "EvilDragon",
            "commit": "08a22ee",
            "date": "2026-05-26T10:34:08+02:00",
            "message": "Various UI/UX improvements for Surge XT Effects (#8400)"
        },
        {
            "author": "EvilDragon",
            "commit": "000f523",
            "date": "2026-05-25T13:35:56+02:00",
            "message": "Store modulator's name in .modpreset (#8398)"
        },
        {
            "author": "EvilDragon",
            "commit": "07d3ea6",
            "date": "2026-05-23T00:13:15+02:00",
            "message": "Accept .modpreset files for drag&drop (#8394)"
        },
        {
            "author": "Bill Allen",
            "commit": "174a672",
            "date": "2026-05-21T16:59:04-04:00",
            "message": "Fix CLI MIDI device discovery on Linux by running a message pump (#8391)"
        }
    ],
    "releases": {
        "linux64": "https://github.com/surge-synthesizer/surge/releases/download/Nightly/surge-xt-linux-x64-NIGHTLY-2026-05-26-8ad24e0.deb",
        "macos": "https://github.com/surge-synthesizer/surge/releases/download/Nightly/surge-xt-macOS-NIGHTLY-2026-05-26-8ad24e0.dmg",
        "win64": "https://github.com/surge-synthesizer/surge/releases/download/Nightly/surge-xt-win64-NIGHTLY-2026-05-26-8ad24e0-setup.exe",
        "win64zip": "https://github.com/surge-synthesizer/surge/releases/download/Nightly/surge-xt-win64-NIGHTLY-2026-05-26-8ad24e0-pluginsonly.zip"
    },
    "version": "NIGHTLY-2026-05-26-8ad24e0"
}