{
    "build_time": "2026-03-30T15:13:46.219625994",
    "data": {},
    "latest_commit": "3c64680",
    "name": "surge-xt",
    "project_repo": "https://github.com/surge-synthesizer/surge",
    "recent_commits": [
        {
            "author": "EvilDragon",
            "commit": "3c64680",
            "date": "2026-03-30T16:24:35+02:00",
            "message": "Move the 2 octave QWERTY layout after QWERTY in the list (#8325)"
        },
        {
            "author": "EvilDragon",
            "commit": "22b2919",
            "date": "2026-03-30T11:53:47+02:00",
            "message": "Add 103 patches from qb (Hijol) (#8324)"
        },
        {
            "author": "nuoun",
            "commit": "4e679ef",
            "date": "2026-03-27T23:16:01+01:00",
            "message": "Fix SQLite -Werror=discarded-qualifiers error for glibc 2.43 (#8320)"
        },
        {
            "author": "EvilDragon",
            "commit": "2165fc9",
            "date": "2026-03-27T11:55:44+01:00",
            "message": "Repaint Multiswitch on mouse drag (#8318)"
        },
        {
            "author": "Joel Blanco Berg",
            "commit": "7577ef7",
            "date": "2026-03-27T00:31:03+01:00",
            "message": "MSEG gate mode fix (#8317)"
        }
    ],
    "releases": {
        "linux64": "https://github.com/surge-synthesizer/surge/releases/download/Nightly/surge-xt-linux-x64-NIGHTLY-2026-03-30-3c64680.deb",
        "macos": "https://github.com/surge-synthesizer/surge/releases/download/Nightly/surge-xt-macOS-NIGHTLY-2026-03-30-3c64680.dmg",
        "win64": "https://github.com/surge-synthesizer/surge/releases/download/Nightly/surge-xt-win64-NIGHTLY-2026-03-30-3c64680-setup.exe",
        "win64zip": "https://github.com/surge-synthesizer/surge/releases/download/Nightly/surge-xt-win64-NIGHTLY-2026-03-30-3c64680-pluginsonly.zip"
    },
    "version": "NIGHTLY-2026-03-30-3c64680"
}